setup.py
cli_bdd/__init__.py
cli_bdd.egg-info/PKG-INFO
cli_bdd.egg-info/SOURCES.txt
cli_bdd.egg-info/dependency_links.txt
cli_bdd.egg-info/requires.txt
cli_bdd.egg-info/top_level.txt
cli_bdd/behave/__init__.py
cli_bdd/behave/steps/__init__.py
cli_bdd/behave/steps/command.py
cli_bdd/behave/steps/environment.py
cli_bdd/behave/steps/file.py
cli_bdd/behave/steps/mixins.py
cli_bdd/core/__init__.py
cli_bdd/core/steps/__init__.py
cli_bdd/core/steps/base.py
cli_bdd/core/steps/command.py
cli_bdd/core/steps/environment.py
cli_bdd/core/steps/file.py
cli_bdd/lettuce/__init__.py
cli_bdd/lettuce/steps/__init__.py
cli_bdd/lettuce/steps/command.py
cli_bdd/lettuce/steps/environment.py
cli_bdd/lettuce/steps/file.py
cli_bdd/lettuce/steps/mixins.py