Metadata-Version: 1.0
Name: cli-bdd
Version: 0.0.4
Summary: BDD for command-line applications
Home-page: https://github.com/chibisov/cli-bdd/
Author: Gennady Chibisov
Author-email: web-chib@ya.ru
License: MIT
Platform: UNKNOWN
